colourz/__init__.py
colourz/__version__.py
colourz/colourz.py
colourz/spinners.py
colourz-1.0.4.dist-info/LICENSE
colourz-1.0.4.dist-info/METADATA
colourz-1.0.4.dist-info/WHEEL
colourz-1.0.4.dist-info/top_level.txt
colourz-1.0.4.dist-info/RECORD
