Metadata-Version: 2.1
Name: colourz
Version: 1.0.4
Summary: Colourz adds coloured text output and spinners to a Windows shell  (Powershell / CMD)
Home-page: https://github.com/alexmacniven/colourz.git
Author: Alex Macniven
Author-email: apmacniven@outlook.com
License: MIT
Platform: UNKNOWN
Classifier: License :: OSI Approved :: MIT License
Classifier: Programming Language :: Python
Classifier: Programming Language :: Python :: 3
Requires-Dist: colorama
